create_icon/__init__.py
create_icon/create_icon.py
create_icon/main.py
create_icon-0.5.3.dist-info/licenses/LICENSE
create_icon-0.5.3.dist-info/METADATA
create_icon-0.5.3.dist-info/WHEEL
create_icon-0.5.3.dist-info/top_level.txt
create_icon-0.5.3.dist-info/RECORD
