Metadata-Version: 2.4
Name: create-icon
Version: 0.5.3
Summary: A simple icon generator to replace the tkinter feather for your programs.
Author: Michael Mulvey (Caveman Software)
License: MIT
Project-URL: Homepage, https://github.com/Caveman-Software/create_icon
Keywords: tkinter,icon,windows,caveman-software
Classifier: Programming Language :: Python :: 3
Classifier: Operating System :: Microsoft :: Windows
Classifier: License :: OSI Approved :: MIT License
Requires-Python: >=3.8
License-File: LICENSE
Dynamic: license-file
